FinRecipes/__init__.py
FinRecipes/evaluate.py
FinRecipes/feature_extraction.py
FinRecipes/models.py
FinRecipes/plots.py
FinRecipes/preprocess.py
FinRecipes/utils.py
FinRecipes-0.0.6.dist-info/LICENSE
FinRecipes-0.0.6.dist-info/METADATA
FinRecipes-0.0.6.dist-info/WHEEL
FinRecipes-0.0.6.dist-info/top_level.txt
FinRecipes-0.0.6.dist-info/RECORD
