Metadata-Version: 2.1
Name: FinRecipes
Version: 0.0.6
Classifier: Development Status :: 4 - Beta
Classifier: License :: OSI Approved :: MIT License
Classifier: Programming Language :: Python :: 3
Classifier: Programming Language :: Python :: 3.6
Classifier: Programming Language :: Python :: 3.7
Classifier: Programming Language :: Python :: 3.8
Classifier: Programming Language :: Python :: 3.9
Classifier: Programming Language :: Python :: 3.10
Classifier: Programming Language :: Python :: 3.11
Classifier: Programming Language :: Python :: 3.12
Classifier: Operating System :: OS Independent
Classifier: Intended Audience :: Science/Research
Classifier: Topic :: Software Development :: Libraries :: Python Modules
License-File: LICENSE
Requires-Dist: pandas
Requires-Dist: progressbar
Requires-Dist: yfinance
Requires-Dist: stockstats
Requires-Dist: datetime
Requires-Dist: pytz
Requires-Dist: numpy
Requires-Dist: tables
Requires-Dist: seaborn >=0.13.2
